setup.cfg
setup.py
paralleltd/Mps.py
paralleltd/ToolFunc.py
paralleltd/__init__.py
paralleltd.egg-info/PKG-INFO
paralleltd.egg-info/SOURCES.txt
paralleltd.egg-info/dependency_links.txt
paralleltd.egg-info/not-zip-safe
paralleltd.egg-info/top_level.txt