Metadata-Version: 2.1
Name: paralleltd
Version: 0.0.2
Summary: Run your code parallely
Author: Leslie Pan
Author-email: pankyfk@163.com
